{
    "inicial": "menu",
    "menus": [
        {
            "title": "RH",
            "links": [
                {
                    "link": "menu",
                    "title": "Menus",
                    "icon": "dashboard"
                },
                {
                    "link": "qualificacao",
                    "title": "Qualificações",
                    "icon": "qualificacao"
                },
                {
                    "link": "funcionario-acidente",
                    "title": "Acidentes de trabalho",
                    "icon": "acidente"
                },
                {
                    "link": "empresa",
                    "title": "Empresa",
                    "icon": "empresa"
                },
                {
                    "link": "unidade",
                    "title": "Unidades",
                    "icon": "unidade"
                }
            ]
        }
    ]
}